tetra_model_zoo/__init__.py
tetra_model_zoo/_version.py
tetra_model_zoo/asset_bases.yaml
tetra_model_zoo/requirements-dev.txt
tetra_model_zoo/requirements.txt
tetra_model_zoo/__pycache__/__init__.cpython-38.pyc
tetra_model_zoo/models/__init__.py
tetra_model_zoo/models/_shared/__init__.py
tetra_model_zoo/models/_shared/common.py
tetra_model_zoo/models/_shared/detr/app.py
tetra_model_zoo/models/_shared/detr/coco_label_map.py
tetra_model_zoo/models/_shared/detr/demo.py
tetra_model_zoo/models/_shared/detr/model.py
tetra_model_zoo/models/_shared/imagenet_classifier/__init__.py
tetra_model_zoo/models/_shared/imagenet_classifier/app.py
tetra_model_zoo/models/_shared/imagenet_classifier/demo.py
tetra_model_zoo/models/_shared/imagenet_classifier/model.py
tetra_model_zoo/models/_shared/imagenet_classifier/test_utils.py
tetra_model_zoo/models/_shared/mediapipe/__init__.py
tetra_model_zoo/models/_shared/mediapipe/app.py
tetra_model_zoo/models/_shared/mediapipe/utils.py
tetra_model_zoo/models/_shared/repaint/__init__.py
tetra_model_zoo/models/_shared/repaint/app.py
tetra_model_zoo/models/_shared/repaint/demo.py
tetra_model_zoo/models/_shared/super_resolution/app.py
tetra_model_zoo/models/_shared/super_resolution/demo.py
tetra_model_zoo/models/_shared/swin/swin_transformer.py
tetra_model_zoo/models/_shared/video_classifier/__init__.py
tetra_model_zoo/models/_shared/video_classifier/app.py
tetra_model_zoo/models/_shared/video_classifier/demo.py
tetra_model_zoo/models/_shared/video_classifier/model.py
tetra_model_zoo/models/_shared/yolo/__init__.py
tetra_model_zoo/models/_shared/yolo/app.py
tetra_model_zoo/models/_shared/yolo/demo.py
tetra_model_zoo/models/_shared/yolo/utils.py
tetra_model_zoo/models/aotgan/README.md
tetra_model_zoo/models/aotgan/__init__.py
tetra_model_zoo/models/aotgan/demo.py
tetra_model_zoo/models/aotgan/export.py
tetra_model_zoo/models/aotgan/model.py
tetra_model_zoo/models/aotgan/test.py
tetra_model_zoo/models/convnext_tiny/README.md
tetra_model_zoo-0.1.5.dist-info/LICENSE
tetra_model_zoo-0.1.5.dist-info/METADATA
tetra_model_zoo-0.1.5.dist-info/WHEEL
tetra_model_zoo-0.1.5.dist-info/top_level.txt
tetra_model_zoo-0.1.5.dist-info/RECORD
