Metadata-Version: 2.1
Name: tetra-model-zoo
Version: 0.1.5
Summary: Models optimized for export to run on device.
Home-page: https://tetra.ai/
Author: Tetra Intelligence Systems Inc.
License: MIT
Requires-Python: >=3.8, <3.11
License-File: LICENSE
Requires-Dist: Pillow ==10.0.1
Requires-Dist: numpy ==1.23.1
Requires-Dist: opencv-python ==4.8.1.78
Requires-Dist: torch <=1.13.1,>=1.11.0
Requires-Dist: gitpython
Requires-Dist: pytest ==7.4.2
Requires-Dist: requests
Requires-Dist: requests-toolbelt
Requires-Dist: torchvision <=0.14.1
Requires-Dist: tetra-hub
Requires-Dist: gdown ==4.7.1
Requires-Dist: pyyaml
Requires-Dist: schema
Requires-Dist: urllib3 <2
Provides-Extra: detr-resnet101
Requires-Dist: transformers ==4.31.0 ; extra == 'detr-resnet101'
Requires-Dist: timm ==0.9.7 ; extra == 'detr-resnet101'
Provides-Extra: detr-resnet101-dc5
Requires-Dist: transformers ==4.31.0 ; extra == 'detr-resnet101-dc5'
Requires-Dist: timm ==0.9.7 ; extra == 'detr-resnet101-dc5'
Provides-Extra: detr-resnet50
Requires-Dist: transformers ==4.31.0 ; extra == 'detr-resnet50'
Requires-Dist: timm ==0.9.7 ; extra == 'detr-resnet50'
Provides-Extra: detr-resnet50-dc5
Requires-Dist: transformers ==4.31.0 ; extra == 'detr-resnet50-dc5'
Requires-Dist: timm ==0.9.7 ; extra == 'detr-resnet50-dc5'
Provides-Extra: detr_resnet101
Requires-Dist: transformers ==4.31.0 ; extra == 'detr_resnet101'
Requires-Dist: timm ==0.9.7 ; extra == 'detr_resnet101'
Provides-Extra: detr_resnet101_dc5
Requires-Dist: transformers ==4.31.0 ; extra == 'detr_resnet101_dc5'
Requires-Dist: timm ==0.9.7 ; extra == 'detr_resnet101_dc5'
Provides-Extra: detr_resnet50
Requires-Dist: transformers ==4.31.0 ; extra == 'detr_resnet50'
Requires-Dist: timm ==0.9.7 ; extra == 'detr_resnet50'
Provides-Extra: detr_resnet50_dc5
Requires-Dist: transformers ==4.31.0 ; extra == 'detr_resnet50_dc5'
Requires-Dist: timm ==0.9.7 ; extra == 'detr_resnet50_dc5'
Provides-Extra: dev
Requires-Dist: coverage ==6.5.0 ; extra == 'dev'
Requires-Dist: pytest-xdist ==3.3.1 ; extra == 'dev'
Requires-Dist: pytest-cov ==4.1.0 ; extra == 'dev'
Requires-Dist: schema ==0.7.5 ; extra == 'dev'
Requires-Dist: pyyaml ==6.0.1 ; extra == 'dev'
Provides-Extra: facebook-denoiser
Requires-Dist: denoiser ; extra == 'facebook-denoiser'
Requires-Dist: torchaudio ; extra == 'facebook-denoiser'
Requires-Dist: PySoundFile ; (sys_platform == "win32") and extra == 'facebook-denoiser'
Provides-Extra: facebook_denoiser
Requires-Dist: denoiser ; extra == 'facebook_denoiser'
Requires-Dist: torchaudio ; extra == 'facebook_denoiser'
Requires-Dist: PySoundFile ; (sys_platform == "win32") and extra == 'facebook_denoiser'
Provides-Extra: huggingface-wavlm-base-plus
Requires-Dist: transformers >=4.31.0 ; extra == 'huggingface-wavlm-base-plus'
Requires-Dist: soundfile >=0.12.1 ; extra == 'huggingface-wavlm-base-plus'
Requires-Dist: librosa >=0.10.1 ; extra == 'huggingface-wavlm-base-plus'
Requires-Dist: datasets >=2.14.5 ; extra == 'huggingface-wavlm-base-plus'
Provides-Extra: huggingface_wavlm_base_plus
Requires-Dist: transformers >=4.31.0 ; extra == 'huggingface_wavlm_base_plus'
Requires-Dist: soundfile >=0.12.1 ; extra == 'huggingface_wavlm_base_plus'
Requires-Dist: librosa >=0.10.1 ; extra == 'huggingface_wavlm_base_plus'
Requires-Dist: datasets >=2.14.5 ; extra == 'huggingface_wavlm_base_plus'
Provides-Extra: lama-dilated
Requires-Dist: matplotlib ; extra == 'lama-dilated'
Requires-Dist: pandas ; extra == 'lama-dilated'
Requires-Dist: albumentations ==0.5.2 ; extra == 'lama-dilated'
Requires-Dist: pytorch-lightning ==1.6.0 ; extra == 'lama-dilated'
Requires-Dist: webdataset ; extra == 'lama-dilated'
Requires-Dist: easydict ==1.10 ; extra == 'lama-dilated'
Requires-Dist: kornia ==0.5.0 ; extra == 'lama-dilated'
Requires-Dist: omegaconf ==2.3.0 ; extra == 'lama-dilated'
Requires-Dist: scikit-learn ==1.3.0 ; extra == 'lama-dilated'
Provides-Extra: lama_dilated
Requires-Dist: matplotlib ; extra == 'lama_dilated'
Requires-Dist: pandas ; extra == 'lama_dilated'
Requires-Dist: albumentations ==0.5.2 ; extra == 'lama_dilated'
Requires-Dist: pytorch-lightning ==1.6.0 ; extra == 'lama_dilated'
Requires-Dist: webdataset ; extra == 'lama_dilated'
Requires-Dist: easydict ==1.10 ; extra == 'lama_dilated'
Requires-Dist: kornia ==0.5.0 ; extra == 'lama_dilated'
Requires-Dist: omegaconf ==2.3.0 ; extra == 'lama_dilated'
Requires-Dist: scikit-learn ==1.3.0 ; extra == 'lama_dilated'
Provides-Extra: litehrnet
Requires-Dist: mmpose <=1.2.0 ; extra == 'litehrnet'
Requires-Dist: mmcv <=2.1.0 ; extra == 'litehrnet'
Requires-Dist: mmdet <=3.2.0 ; extra == 'litehrnet'
Provides-Extra: mediapipe-face
Requires-Dist: opencv-python ; extra == 'mediapipe-face'
Requires-Dist: requests ; extra == 'mediapipe-face'
Provides-Extra: mediapipe-hand
Requires-Dist: opencv-python ; extra == 'mediapipe-hand'
Requires-Dist: requests ; extra == 'mediapipe-hand'
Provides-Extra: mediapipe-pose
Requires-Dist: opencv-python ; extra == 'mediapipe-pose'
Requires-Dist: requests ; extra == 'mediapipe-pose'
Provides-Extra: mediapipe-selfie
Requires-Dist: tflite ==2.10.0 ; extra == 'mediapipe-selfie'
Provides-Extra: mediapipe_face
Requires-Dist: opencv-python ; extra == 'mediapipe_face'
Requires-Dist: requests ; extra == 'mediapipe_face'
Provides-Extra: mediapipe_hand
Requires-Dist: opencv-python ; extra == 'mediapipe_hand'
Requires-Dist: requests ; extra == 'mediapipe_hand'
Provides-Extra: mediapipe_pose
Requires-Dist: opencv-python ; extra == 'mediapipe_pose'
Requires-Dist: requests ; extra == 'mediapipe_pose'
Provides-Extra: mediapipe_selfie
Requires-Dist: tflite ==2.10.0 ; extra == 'mediapipe_selfie'
Provides-Extra: mobiledet
Requires-Dist: tucker-conv ==1.0.1 ; extra == 'mobiledet'
Requires-Dist: timm ==0.6.13 ; extra == 'mobiledet'
Provides-Extra: openai-clip
Requires-Dist: clip-by-openai ==0.1.1.5 ; extra == 'openai-clip'
Requires-Dist: torchvision ; extra == 'openai-clip'
Provides-Extra: openai_clip
Requires-Dist: clip-by-openai ==0.1.1.5 ; extra == 'openai_clip'
Requires-Dist: torchvision ; extra == 'openai_clip'
Provides-Extra: openpose
Requires-Dist: scipy ; extra == 'openpose'
Requires-Dist: matplotlib ; extra == 'openpose'
Provides-Extra: optimized-clip
Requires-Dist: ane-transformers ==0.1.3 ; extra == 'optimized-clip'
Requires-Dist: clip-by-openai ==0.1.1.5 ; extra == 'optimized-clip'
Provides-Extra: optimized_clip
Requires-Dist: ane-transformers ==0.1.3 ; extra == 'optimized_clip'
Requires-Dist: clip-by-openai ==0.1.1.5 ; extra == 'optimized_clip'
Provides-Extra: real-esrgan-general-x4v3
Requires-Dist: opencv-python ; extra == 'real-esrgan-general-x4v3'
Requires-Dist: PyYAML ; extra == 'real-esrgan-general-x4v3'
Requires-Dist: requests ; extra == 'real-esrgan-general-x4v3'
Requires-Dist: scipy ; extra == 'real-esrgan-general-x4v3'
Requires-Dist: seaborn ; extra == 'real-esrgan-general-x4v3'
Requires-Dist: basicsr ; extra == 'real-esrgan-general-x4v3'
Provides-Extra: real-esrgan-x4plus
Requires-Dist: opencv-python ; extra == 'real-esrgan-x4plus'
Requires-Dist: scipy ; extra == 'real-esrgan-x4plus'
Requires-Dist: seaborn ; extra == 'real-esrgan-x4plus'
Requires-Dist: basicsr ; extra == 'real-esrgan-x4plus'
Provides-Extra: real_esrgan_general_x4v3
Requires-Dist: opencv-python ; extra == 'real_esrgan_general_x4v3'
Requires-Dist: PyYAML ; extra == 'real_esrgan_general_x4v3'
Requires-Dist: requests ; extra == 'real_esrgan_general_x4v3'
Requires-Dist: scipy ; extra == 'real_esrgan_general_x4v3'
Requires-Dist: seaborn ; extra == 'real_esrgan_general_x4v3'
Requires-Dist: basicsr ; extra == 'real_esrgan_general_x4v3'
Provides-Extra: real_esrgan_x4plus
Requires-Dist: opencv-python ; extra == 'real_esrgan_x4plus'
Requires-Dist: scipy ; extra == 'real_esrgan_x4plus'
Requires-Dist: seaborn ; extra == 'real_esrgan_x4plus'
Requires-Dist: basicsr ; extra == 'real_esrgan_x4plus'
Provides-Extra: resnet-2plus1d
Requires-Dist: av ==10.0.0 ; extra == 'resnet-2plus1d'
Provides-Extra: resnet-3d
Requires-Dist: av ==10.0.0 ; extra == 'resnet-3d'
Provides-Extra: resnet-mixed
Requires-Dist: av ==10.0.0 ; extra == 'resnet-mixed'
Provides-Extra: resnet_2plus1d
Requires-Dist: av ==10.0.0 ; extra == 'resnet_2plus1d'
Provides-Extra: resnet_3d
Requires-Dist: av ==10.0.0 ; extra == 'resnet_3d'
Provides-Extra: resnet_mixed
Requires-Dist: av ==10.0.0 ; extra == 'resnet_mixed'
Provides-Extra: sam
Requires-Dist: matplotlib ; extra == 'sam'
Requires-Dist: opencv-python ; extra == 'sam'
Requires-Dist: pycocotools ; extra == 'sam'
Requires-Dist: requests ; extra == 'sam'
Provides-Extra: stable-diffusion
Requires-Dist: transformers ==4.31.0 ; extra == 'stable-diffusion'
Requires-Dist: coremltools ==6.2 ; extra == 'stable-diffusion'
Requires-Dist: diffusers[torch] ==0.21.4 ; extra == 'stable-diffusion'
Provides-Extra: stable_diffusion
Requires-Dist: transformers ==4.31.0 ; extra == 'stable_diffusion'
Requires-Dist: coremltools ==6.2 ; extra == 'stable_diffusion'
Requires-Dist: diffusers[torch] ==0.21.4 ; extra == 'stable_diffusion'
Provides-Extra: trocr
Requires-Dist: transformers ==4.33.2 ; extra == 'trocr'
Requires-Dist: sentencepiece ; extra == 'trocr'
Provides-Extra: whisper-asr
Requires-Dist: openai-whisper ==20230314 ; extra == 'whisper-asr'
Requires-Dist: scipy ; extra == 'whisper-asr'
Provides-Extra: whisper_asr
Requires-Dist: openai-whisper ==20230314 ; extra == 'whisper_asr'
Requires-Dist: scipy ; extra == 'whisper_asr'
Provides-Extra: yolov7
Requires-Dist: matplotlib ; extra == 'yolov7'
Requires-Dist: opencv-python ; extra == 'yolov7'
Requires-Dist: PyYAML ; extra == 'yolov7'
Requires-Dist: requests ; extra == 'yolov7'
Requires-Dist: scipy ; extra == 'yolov7'
Requires-Dist: seaborn ; extra == 'yolov7'
Provides-Extra: yolov8-det
Requires-Dist: ultralytics ==8.0.193 ; extra == 'yolov8-det'
Provides-Extra: yolov8_det
Requires-Dist: ultralytics ==8.0.193 ; extra == 'yolov8_det'
